imgspy.py
imgspy-0.2.2.dist-info/METADATA
imgspy-0.2.2.dist-info/WHEEL
imgspy-0.2.2.dist-info/top_level.txt
imgspy-0.2.2.dist-info/RECORD
