Metadata-Version: 2.1
Name: imgspy
Version: 0.2.2
Summary: Find the size or type of the image without fetching the whole content.
Home-page: https://github.com/nkanaev/imgspy
Author: Nazar Kanaev
Author-email: nkanaev@live.com
License: MIT
Keywords: fastimage image size
Platform: UNKNOWN
Classifier: Development Status :: 4 - Beta
Classifier: Intended Audience :: Developers
Classifier: License :: OSI Approved :: MIT License
Classifier: Operating System :: OS Independent
Classifier: Programming Language :: Python
Classifier: Programming Language :: Python :: 2.7
Classifier: Programming Language :: Python :: 3.6
Classifier: Topic :: Software Development :: Libraries :: Python Modules
